Metadata-Version: 2.4
Name: celery-asyncio
Version: 6.0.0a1
Summary: Distributed Task Queue with native asyncio support
Project-URL: Changelog, https://github.com/oliverhaas/celery/blob/main-asyncio/Changelog.rst
Project-URL: Documentation, https://docs.celeryq.dev/en/stable/
Project-URL: Source, https://github.com/oliverhaas/celery/tree/main-asyncio
Project-URL: Tracker, https://github.com/oliverhaas/celery/issues
Author-email: Ask Solem <auvipy@gmail.com>
License-Expression: BSD-3-Clause
License-File: LICENSE
Keywords: actors,amqp,async,asyncio,distributed,job,python,queue,rabbitmq,redis,task
Classifier: Development Status :: 3 - Alpha
Classifier: Framework :: AsyncIO
Classifier: Framework :: Celery
Classifier: Intended Audience :: Developers
Classifier: License :: OSI Approved :: BSD License
Classifier: Operating System :: OS Independent
Classifier: Programming Language :: Python :: 3
Classifier: Programming Language :: Python :: 3 :: Only
Classifier: Programming Language :: Python :: 3.10
Classifier: Programming Language :: Python :: 3.11
Classifier: Programming Language :: Python :: 3.12
Classifier: Programming Language :: Python :: 3.13
Classifier: Programming Language :: Python :: Implementation :: CPython
Classifier: Topic :: Software Development :: Object Brokering
Classifier: Topic :: System :: Distributed Computing
Requires-Python: >=3.10
Requires-Dist: billiard<5.0,>=4.2.1
Requires-Dist: click-didyoumean>=0.3.0
Requires-Dist: click-plugins>=1.1.1
Requires-Dist: click-repl>=0.2.0
Requires-Dist: click<9.0,>=8.1.2
Requires-Dist: kombu-asyncio>=6.0.0a1
Requires-Dist: python-dateutil>=2.8.2
Requires-Dist: tzlocal
Requires-Dist: vine<6.0,>=5.1.0
Provides-Extra: arangodb
Requires-Dist: pyarango>=2.0.2; extra == 'arangodb'
Provides-Extra: auth
Requires-Dist: cryptography; extra == 'auth'
Provides-Extra: azureblockblob
Requires-Dist: azure-storage-blob>=12.15.0; extra == 'azureblockblob'
Provides-Extra: brotli
Requires-Dist: brotli>=1.0.0; extra == 'brotli'
Provides-Extra: cassandra
Requires-Dist: cassandra-driver>=3.25.0; extra == 'cassandra'
Provides-Extra: consul
Requires-Dist: python-consul2; extra == 'consul'
Provides-Extra: cosmosdbsql
Requires-Dist: pydocumentdb>=2.3.5; extra == 'cosmosdbsql'
Provides-Extra: couchbase
Requires-Dist: couchbase>=3.0.0; extra == 'couchbase'
Provides-Extra: couchdb
Requires-Dist: pycouchdb; extra == 'couchdb'
Provides-Extra: django
Requires-Dist: django>=4.2; extra == 'django'
Provides-Extra: dynamodb
Requires-Dist: boto3>=1.26.143; extra == 'dynamodb'
Provides-Extra: elasticsearch
Requires-Dist: elasticsearch>=7.0.0; extra == 'elasticsearch'
Provides-Extra: eventlet
Requires-Dist: eventlet>=0.32.0; extra == 'eventlet'
Provides-Extra: gcs
Requires-Dist: google-cloud-storage>=2.10.0; extra == 'gcs'
Provides-Extra: gevent
Requires-Dist: gevent>=1.5.0; extra == 'gevent'
Provides-Extra: memcache
Requires-Dist: pylibmc; extra == 'memcache'
Provides-Extra: mongodb
Requires-Dist: kombu-asyncio[mongodb]; extra == 'mongodb'
Provides-Extra: msgpack
Requires-Dist: msgpack; extra == 'msgpack'
Provides-Extra: pymemcache
Requires-Dist: python-memcached; extra == 'pymemcache'
Provides-Extra: pytest
Requires-Dist: pytest>=8.0.0; extra == 'pytest'
Provides-Extra: redis
Requires-Dist: kombu-asyncio[redis]; extra == 'redis'
Provides-Extra: s3
Requires-Dist: boto3>=1.26.143; extra == 's3'
Provides-Extra: sqlalchemy
Requires-Dist: kombu-asyncio[sqlalchemy]; extra == 'sqlalchemy'
Requires-Dist: sqlalchemy>=1.4.0; extra == 'sqlalchemy'
Provides-Extra: sqs
Requires-Dist: boto3>=1.26.143; extra == 'sqs'
Requires-Dist: kombu-asyncio[sqs]>=6.0.0a1; extra == 'sqs'
Requires-Dist: pycurl>=7.45.4; (sys_platform != 'win32' and platform_python_implementation == 'CPython') and extra == 'sqs'
Requires-Dist: urllib3>=1.26.16; extra == 'sqs'
Provides-Extra: tblib
Requires-Dist: tblib>=1.3.0; extra == 'tblib'
Provides-Extra: yaml
Requires-Dist: pyyaml>=3.10; extra == 'yaml'
Provides-Extra: zstd
Requires-Dist: zstandard>=0.22.0; extra == 'zstd'
